[
  {
    "id": "TASK-3697",
    "code": "41VhVR14Xd",
    "qr": [
      "kzK6Hlx2Ys",
      "RHaSb6OnUp"
    ],
    "title": "Try to index the IP application, maybe it will hack the open-source hard drive!",
    "category": "marketing",
    "type": "Email",
    "created_by": "Elody Ernser",
    "date_created": "2024-10-09T08:40:17.935Z",
    "origin_office": "branch_office",
    "status": "recieved"
  },
  {
    "id": "TASK-6843",
    "code": "oXwIryKYBK",
    "qr": [
      "bSPkAxwj3q",
      "1Rq4MLc1ex"
    ],
    "title": "Try to index the IB capacitor, maybe it will navigate the 1080p matrix!",
    "category": "legal",
    "type": "Report",
    "created_by": "Deborah Kutch",
    "date_created": "2024-10-26T00:27:58.383Z",
    "origin_office": "branch_office",
    "status": "completed"
  },
  {
    "id": "TASK-2254",
    "code": "OXAoPSyarL",
    "qr": [
      "oe2I8015Pb",
      "S2UlpUzDmH"
    ],
    "title": "We need to program the mobile DNS application!",
    "category": "legal",
    "type": "Report",
    "created_by": "Tania Wehner",
    "date_created": "2024-10-06T03:40:37.037Z",
    "origin_office": "branch_office",
    "status": "completed"
  },
  {
    "id": "TASK-8092",
    "code": "aoZLtX9mwp",
    "qr": [
      "I6enmByk3M",
      "0MR1Kj2dEx"
    ],
    "title": "We need to connect the primary XSS transmitter!",
    "category": "financial",
    "type": "Report",
    "created_by": "Porter Powlowski",
    "date_created": "2024-10-15T13:57:42.221Z",
    "origin_office": "header_office",
    "status": "incoming"
  },
  {
    "id": "TASK-9844",
    "code": "Hs5kW6ldea",
    "qr": [
      "ZAYO7eLvSM",
      "ae9xYTKXBM"
    ],
    "title": "Use the back-end CSS port, then you can calculate the digital card!",
    "category": "marketing",
    "type": "Document",
    "created_by": "Magali Stamm",
    "date_created": "2024-10-27T19:44:14.956Z",
    "origin_office": "regional_office",
    "status": "recieved"
  },
  {
    "id": "TASK-9264",
    "code": "KbfmHUM7AS",
    "qr": [
      "ySA9rJNkCG",
      "y8UgwEEMTy"
    ],
    "title": "The ADP panel is down, back up the online firewall so we can calculate the IB sensor!",
    "category": "confidential",
    "type": "Document",
    "created_by": "Sterling Rodriguez",
    "date_created": "2024-10-14T13:08:09.039Z",
    "origin_office": "branch_office",
    "status": "recieved"
  },
  {
    "id": "TASK-6333",
    "code": "6kH9CvhtH6",
    "qr": [
      "DMdSw6tcxI",
      "OaTCNxqr0u"
    ],
    "title": "We need to index the optical HEX pixel!",
    "category": "hr",
    "type": "Report",
    "created_by": "Emil Koss",
    "date_created": "2024-11-01T01:10:47.906Z",
    "origin_office": "branch_office",
    "status": "recieved"
  },
  {
    "id": "TASK-1319",
    "code": "uat8fpigos",
    "qr": [
      "6AATxaJPWg",
      "OMVt3MgzAx"
    ],
    "title": "You can't back up the pixel without copying the bluetooth OCR card!",
    "category": "marketing",
    "type": "Document",
    "created_by": "Luis Corkery",
    "date_created": "2024-10-26T16:49:28.092Z",
    "origin_office": "regional_office",
    "status": "completed"
  },
  {
    "id": "TASK-3380",
    "code": "TTqmWg6PCE",
    "qr": [
      "s2PLwqRurn",
      "HwPJFZQ8q0"
    ],
    "title": "Bypassing the alarm won't do anything, we need to override the redundant UTF8 port!",
    "category": "hr",
    "type": "Document",
    "created_by": "Josefina Rosenbaum",
    "date_created": "2024-10-17T10:02:02.750Z",
    "origin_office": "header_office",
    "status": "completed"
  },
  {
    "id": "TASK-2467",
    "code": "nUnyr1FbF7",
    "qr": [
      "iOtasSNp8L",
      "WrMaAI5lz2"
    ],
    "title": "Copying the alarm won't do anything, we need to hack the multi-byte JBOD feed!",
    "category": "confidential",
    "type": "Email",
    "created_by": "Deondre Wunsch-Fahey",
    "date_created": "2024-10-30T10:35:46.080Z",
    "origin_office": "branch_office",
    "status": "outgoing"
  },
  {
    "id": "TASK-8890",
    "code": "EHEM3FNHlA",
    "qr": [
      "Rd6RWAroAD",
      "QEJS9rxlft"
    ],
    "title": "We need to hack the digital SAS system!",
    "category": "confidential",
    "type": "Meeting",
    "created_by": "Maci O'Conner",
    "date_created": "2024-10-30T09:15:18.456Z",
    "origin_office": "header_office",
    "status": "completed"
  },
  {
    "id": "TASK-4446",
    "code": "mnwkRedTou",
    "qr": [
      "5XdVBn1yq6",
      "uPOuHKTkFJ"
    ],
    "title": "The ADP hard drive is down, back up the open-source card so we can index the DRAM protocol!",
    "category": "hr",
    "type": "Report",
    "created_by": "Alexa Bednar",
    "date_created": "2024-10-16T22:43:02.964Z",
    "origin_office": "regional_office",
    "status": "outgoing"
  },
  {
    "id": "TASK-6004",
    "code": "UnGQ9A3uGv",
    "qr": [
      "pDUhAQhnug",
      "Q1jnTKWzqq"
    ],
    "title": "You can't navigate the sensor without transmitting the bluetooth SSD alarm!",
    "category": "hr",
    "type": "Meeting",
    "created_by": "Justine Ledner",
    "date_created": "2024-10-07T00:18:12.391Z",
    "origin_office": "regional_office",
    "status": "completed"
  },
  {
    "id": "TASK-7415",
    "code": "cHSD0F0kAl",
    "qr": [
      "PSxRJTh6ud",
      "vOVrZlQ61x"
    ],
    "title": "If we transmit the port, we can get to the RSS circuit through the redundant IP interface!",
    "category": "marketing",
    "type": "Meeting",
    "created_by": "Candido Jones",
    "date_created": "2024-10-30T21:09:06.739Z",
    "origin_office": "branch_office",
    "status": "recieved"
  },
  {
    "id": "TASK-8541",
    "code": "Tef4EDF6d5",
    "qr": [
      "G823LKOp5k",
      "8WsHPavMEU"
    ],
    "title": "We need to copy the multi-byte HEX system!",
    "category": "financial",
    "type": "Document",
    "created_by": "Robbie Tremblay",
    "date_created": "2024-10-23T00:27:30.281Z",
    "origin_office": "regional_office",
    "status": "completed"
  },
  {
    "id": "TASK-3576",
    "code": "l4F7HLoS2i",
    "qr": [
      "UPErB9RVti",
      "yRzgWBMKvU"
    ],
    "title": "Generating the panel won't do anything, we need to bypass the online SSL capacitor!",
    "category": "financial",
    "type": "Email",
    "created_by": "Ilene Hackett",
    "date_created": "2024-10-13T22:34:47.120Z",
    "origin_office": "header_office",
    "status": "recieved"
  },
  {
    "id": "TASK-4536",
    "code": "2UbJxK11sM",
    "qr": [
      "NwkqUsfwbB",
      "AqC0PtldNv"
    ],
    "title": "If we quantify the protocol, we can get to the SQL circuit through the solid state JBOD system!",
    "category": "legal",
    "type": "Email",
    "created_by": "Mossie Wisozk",
    "date_created": "2024-10-24T04:26:55.911Z",
    "origin_office": "header_office",
    "status": "incoming"
  },
  {
    "id": "TASK-2448",
    "code": "zeQTSygRRh",
    "qr": [
      "gNhpIXe1zY",
      "LxSM57G0Fm"
    ],
    "title": "The HDD system is down, quantify the wireless port so we can parse the XSS protocol!",
    "category": "financial",
    "type": "Meeting",
    "created_by": "Jensen Mosciski",
    "date_created": "2024-10-19T00:46:31.490Z",
    "origin_office": "regional_office",
    "status": "outgoing"
  },
  {
    "id": "TASK-2100",
    "code": "5Bq7e70kob",
    "qr": [
      "o4OLZUmhUt",
      "39v3clXCD5"
    ],
    "title": "Use the multi-byte ASCII driver, then you can compress the wireless microchip!",
    "category": "financial",
    "type": "Email",
    "created_by": "Julia McCullough",
    "date_created": "2024-10-10T06:36:43.758Z",
    "origin_office": "regional_office",
    "status": "incoming"
  },
  {
    "id": "TASK-7336",
    "code": "SRYsSMp6dw",
    "qr": [
      "CBBBqhYQql",
      "JFNJRkE4qV"
    ],
    "title": "I'll override the solid state OCR protocol, that should firewall the OCR interface!",
    "category": "hr",
    "type": "Report",
    "created_by": "Lucile Stark",
    "date_created": "2024-10-22T00:57:46.232Z",
    "origin_office": "header_office",
    "status": "incoming"
  },
  {
    "id": "TASK-5601",
    "code": "P3EZWmR3rv",
    "qr": [
      "hjU6OofBBJ",
      "OyBbhReMzr"
    ],
    "title": "Quantifying the transmitter won't do anything, we need to transmit the virtual HEX alarm!",
    "category": "financial",
    "type": "Document",
    "created_by": "Elise Murphy",
    "date_created": "2024-10-28T21:59:19.766Z",
    "origin_office": "branch_office",
    "status": "completed"
  },
  {
    "id": "TASK-9812",
    "code": "FWWeCKXuQI",
    "qr": [
      "AKoRUthm3Y",
      "h9e3WlhZOe"
    ],
    "title": "You can't connect the matrix without copying the neural ASCII alarm!",
    "category": "legal",
    "type": "Document",
    "created_by": "Marques Rice",
    "date_created": "2024-10-07T20:00:03.345Z",
    "origin_office": "branch_office",
    "status": "incoming"
  },
  {
    "id": "TASK-8075",
    "code": "XmM7PlO4ch",
    "qr": [
      "D0fdsqemaW",
      "TDlpPYrTLe"
    ],
    "title": "You can't back up the card without quantifying the cross-platform VGA card!",
    "category": "financial",
    "type": "Report",
    "created_by": "Antonio Kassulke",
    "date_created": "2024-10-14T12:44:47.335Z",
    "origin_office": "regional_office",
    "status": "outgoing"
  },
  {
    "id": "TASK-2539",
    "code": "fuP9DQD4Mk",
    "qr": [
      "olWLSif4jA",
      "LcP01MvBdc"
    ],
    "title": "Use the redundant SSD port, then you can input the cross-platform system!",
    "category": "hr",
    "type": "Document",
    "created_by": "Stefan Herman",
    "date_created": "2024-10-23T04:48:34.631Z",
    "origin_office": "branch_office",
    "status": "incoming"
  },
  {
    "id": "TASK-3669",
    "code": "07Ry0NeEK7",
    "qr": [
      "nzliR9jJuu",
      "fm3LhnwZvE"
    ],
    "title": "Programming the driver won't do anything, we need to bypass the haptic OCR panel!",
    "category": "marketing",
    "type": "Email",
    "created_by": "Sherman Hickle",
    "date_created": "2024-10-08T01:24:32.801Z",
    "origin_office": "header_office",
    "status": "outgoing"
  },
  {
    "id": "TASK-1469",
    "code": "tzNTInvDbx",
    "qr": [
      "fnPyYhNJF1",
      "WIP78TJINm"
    ],
    "title": "We need to input the virtual IB microchip!",
    "category": "financial",
    "type": "Email",
    "created_by": "Chanel Crist",
    "date_created": "2024-10-21T09:29:00.264Z",
    "origin_office": "regional_office",
    "status": "completed"
  },
  {
    "id": "TASK-3706",
    "code": "zlLjgyc1cS",
    "qr": [
      "mhJAiHJFQr",
      "Bd1PEjyMRo"
    ],
    "title": "Try to override the TLS alarm, maybe it will synthesize the wireless matrix!",
    "category": "confidential",
    "type": "Document",
    "created_by": "Sean Osinski",
    "date_created": "2024-10-14T08:15:25.911Z",
    "origin_office": "branch_office",
    "status": "recieved"
  },
  {
    "id": "TASK-9948",
    "code": "lT5FtXBrWo",
    "qr": [
      "1BxgZ6Aice",
      "HfVx5BtUFl"
    ],
    "title": "The PCI matrix is down, hack the cross-platform microchip so we can override the TCP program!",
    "category": "hr",
    "type": "Email",
    "created_by": "Zane Stokes",
    "date_created": "2024-10-10T22:42:45.472Z",
    "origin_office": "branch_office",
    "status": "completed"
  },
  {
    "id": "TASK-2445",
    "code": "IThWr74IHq",
    "qr": [
      "PBje0SSvOJ",
      "TZGBhwTi0w"
    ],
    "title": "I'll copy the solid state SMS protocol, that should driver the JSON capacitor!",
    "category": "hr",
    "type": "Email",
    "created_by": "Davon Schmeler",
    "date_created": "2024-10-15T03:58:25.225Z",
    "origin_office": "header_office",
    "status": "incoming"
  },
  {
    "id": "TASK-2252",
    "code": "Tg2K4cwHgP",
    "qr": [
      "hzgNucuGd7",
      "LB6P8ly4Fo"
    ],
    "title": "If we bypass the hard drive, we can get to the EXE sensor through the bluetooth FTP firewall!",
    "category": "confidential",
    "type": "Meeting",
    "created_by": "Lillie Halvorson",
    "date_created": "2024-10-07T23:14:29.044Z",
    "origin_office": "regional_office",
    "status": "completed"
  },
  {
    "id": "TASK-8232",
    "code": "Aj8xTvgmns",
    "qr": [
      "JezwJsPCNC",
      "39RFXzcHzp"
    ],
    "title": "Navigating the pixel won't do anything, we need to synthesize the digital PNG firewall!",
    "category": "confidential",
    "type": "Email",
    "created_by": "Felipe Wilderman",
    "date_created": "2024-10-05T02:50:10.480Z",
    "origin_office": "regional_office",
    "status": "outgoing"
  },
  {
    "id": "TASK-8523",
    "code": "0bbSq3BaoQ",
    "qr": [
      "KbaFdFwnSj",
      "rb9GoXWCqb"
    ],
    "title": "Use the multi-byte AGP circuit, then you can input the auxiliary card!",
    "category": "legal",
    "type": "Email",
    "created_by": "Naomi Borer",
    "date_created": "2024-10-22T05:56:20.251Z",
    "origin_office": "header_office",
    "status": "recieved"
  },
  {
    "id": "TASK-5162",
    "code": "YS4bs8BXDc",
    "qr": [
      "mfjeL8f220",
      "mvLCdNarVb"
    ],
    "title": "The XSS transmitter is down, synthesize the wireless port so we can parse the SSL driver!",
    "category": "hr",
    "type": "Meeting",
    "created_by": "Daphnee Keeling",
    "date_created": "2024-10-17T18:47:33.437Z",
    "origin_office": "regional_office",
    "status": "recieved"
  },
  {
    "id": "TASK-1199",
    "code": "YdgzqWeLXO",
    "qr": [
      "FgrlcYJboD",
      "f8qedtbUBz"
    ],
    "title": "The SSD pixel is down, back up the mobile alarm so we can copy the VGA bandwidth!",
    "category": "hr",
    "type": "Email",
    "created_by": "Vance Ziemann",
    "date_created": "2024-10-21T20:38:05.482Z",
    "origin_office": "regional_office",
    "status": "incoming"
  },
  {
    "id": "TASK-9890",
    "code": "Vry47830fv",
    "qr": [
      "0LocLEKNm6",
      "9FTMcMBNqI"
    ],
    "title": "If we input the protocol, we can get to the PCI circuit through the mobile SSL card!",
    "category": "confidential",
    "type": "Meeting",
    "created_by": "Nyah Conn",
    "date_created": "2024-10-13T13:10:41.159Z",
    "origin_office": "branch_office",
    "status": "outgoing"
  },
  {
    "id": "TASK-5402",
    "code": "5iWYaaL7No",
    "qr": [
      "FAVwqEzvnz",
      "Djm4uuH0xa"
    ],
    "title": "You can't input the bus without indexing the multi-byte AI panel!",
    "category": "hr",
    "type": "Document",
    "created_by": "Milton McCullough",
    "date_created": "2024-10-30T07:49:36.927Z",
    "origin_office": "header_office",
    "status": "completed"
  },
  {
    "id": "TASK-9999",
    "code": "WwoKu1Sj5s",
    "qr": [
      "uB5Er1q8I5",
      "rh42b4IFVv"
    ],
    "title": "Try to reboot the IP transmitter, maybe it will bypass the back-end driver!",
    "category": "financial",
    "type": "Email",
    "created_by": "Yadira Kulas",
    "date_created": "2024-10-14T02:05:49.015Z",
    "origin_office": "header_office",
    "status": "incoming"
  },
  {
    "id": "TASK-3569",
    "code": "nJ3xRdqhdw",
    "qr": [
      "SQrA4IOZ2p",
      "swZA0pmIEC"
    ],
    "title": "The FTP firewall is down, bypass the virtual alarm so we can input the OCR alarm!",
    "category": "marketing",
    "type": "Meeting",
    "created_by": "Greg Turner",
    "date_created": "2024-10-31T07:58:54.455Z",
    "origin_office": "regional_office",
    "status": "recieved"
  },
  {
    "id": "TASK-3392",
    "code": "Y884nPt9D5",
    "qr": [
      "aVJrS18THD",
      "Ksnl4IOxVu"
    ],
    "title": "You can't back up the bandwidth without quantifying the virtual ADP program!",
    "category": "financial",
    "type": "Email",
    "created_by": "Brennan Kohler",
    "date_created": "2024-10-19T18:27:54.336Z",
    "origin_office": "regional_office",
    "status": "recieved"
  },
  {
    "id": "TASK-4751",
    "code": "XY9J3HTExh",
    "qr": [
      "BnZTqVskIr",
      "vulV3Y6CS5"
    ],
    "title": "Calculating the panel won't do anything, we need to generate the optical UDP driver!",
    "category": "marketing",
    "type": "Report",
    "created_by": "Paolo Gulgowski",
    "date_created": "2024-10-27T09:51:10.284Z",
    "origin_office": "branch_office",
    "status": "recieved"
  },
  {
    "id": "TASK-7216",
    "code": "8pRN3To1DI",
    "qr": [
      "ncDipZajkU",
      "govTUjr6zH"
    ],
    "title": "Try to input the PCI driver, maybe it will index the mobile matrix!",
    "category": "legal",
    "type": "Email",
    "created_by": "Orion Orn",
    "date_created": "2024-10-12T19:41:38.323Z",
    "origin_office": "header_office",
    "status": "incoming"
  },
  {
    "id": "TASK-1459",
    "code": "CutBZD0Erp",
    "qr": [
      "98LEPTl8By",
      "7QkJl4Asxu"
    ],
    "title": "Programming the feed won't do anything, we need to synthesize the wireless JBOD array!",
    "category": "hr",
    "type": "Email",
    "created_by": "Reyna Bahringer",
    "date_created": "2024-10-18T22:48:30.973Z",
    "origin_office": "regional_office",
    "status": "incoming"
  },
  {
    "id": "TASK-1375",
    "code": "Krtww11Qd8",
    "qr": [
      "s0XyAK5fNW",
      "pCjL4K96mo"
    ],
    "title": "I'll program the haptic UDP card, that should feed the DNS protocol!",
    "category": "legal",
    "type": "Meeting",
    "created_by": "Rollin Walter",
    "date_created": "2024-10-22T05:53:18.371Z",
    "origin_office": "branch_office",
    "status": "recieved"
  },
  {
    "id": "TASK-7644",
    "code": "qVUiHhTEuH",
    "qr": [
      "6vkscKsQBc",
      "4CPUgqg9aW"
    ],
    "title": "You can't synthesize the monitor without compressing the 1080p UDP pixel!",
    "category": "confidential",
    "type": "Meeting",
    "created_by": "Jacinto Hagenes",
    "date_created": "2024-10-18T05:57:32.820Z",
    "origin_office": "regional_office",
    "status": "outgoing"
  },
  {
    "id": "TASK-1250",
    "code": "P4GiSPEEP7",
    "qr": [
      "xD90bX7RUT",
      "5Z0Wtb9Bib"
    ],
    "title": "Try to synthesize the CLI panel, maybe it will override the optical bus!",
    "category": "financial",
    "type": "Report",
    "created_by": "Roscoe Towne",
    "date_created": "2024-10-09T19:39:43.464Z",
    "origin_office": "branch_office",
    "status": "recieved"
  },
  {
    "id": "TASK-2132",
    "code": "56DWkkrTPd",
    "qr": [
      "Ex20pVFuvR",
      "fBVWhcq8Iy"
    ],
    "title": "If we generate the circuit, we can get to the GB circuit through the neural SCSI firewall!",
    "category": "hr",
    "type": "Report",
    "created_by": "Kevon Runolfsdottir",
    "date_created": "2024-10-14T20:47:51.821Z",
    "origin_office": "header_office",
    "status": "recieved"
  },
  {
    "id": "TASK-7376",
    "code": "m7En09bMeC",
    "qr": [
      "ieRHF0W8XU",
      "pHgTYOZikz"
    ],
    "title": "Use the multi-byte IB array, then you can compress the haptic protocol!",
    "category": "hr",
    "type": "Document",
    "created_by": "Kirstin Borer",
    "date_created": "2024-10-31T01:34:11.233Z",
    "origin_office": "header_office",
    "status": "outgoing"
  },
  {
    "id": "TASK-5267",
    "code": "8gjHQY73f7",
    "qr": [
      "vk42JPtiNS",
      "nwn0qg42tE"
    ],
    "title": "Try to generate the OCR system, maybe it will calculate the primary transmitter!",
    "category": "financial",
    "type": "Report",
    "created_by": "Jenifer Schuppe",
    "date_created": "2024-10-18T21:55:18.557Z",
    "origin_office": "branch_office",
    "status": "outgoing"
  },
  {
    "id": "TASK-7123",
    "code": "OxvmVnBOcg",
    "qr": [
      "7zQNBrSGzI",
      "BmwHeh0PTH"
    ],
    "title": "Use the multi-byte SSD firewall, then you can navigate the multi-byte capacitor!",
    "category": "confidential",
    "type": "Email",
    "created_by": "Oral Borer-Frami",
    "date_created": "2024-10-23T12:52:26.566Z",
    "origin_office": "header_office",
    "status": "incoming"
  },
  {
    "id": "TASK-9481",
    "code": "ecWOmGpf24",
    "qr": [
      "3dDMFLj3He",
      "rQQCgxU8hQ"
    ],
    "title": "Compressing the driver won't do anything, we need to program the open-source ADP pixel!",
    "category": "financial",
    "type": "Report",
    "created_by": "Dortha Bode",
    "date_created": "2024-10-03T20:45:09.906Z",
    "origin_office": "header_office",
    "status": "recieved"
  },
  {
    "id": "TASK-6979",
    "code": "Bj8OENiaCp",
    "qr": [
      "8JBhxcP7EM",
      "QSfAuyhyW3"
    ],
    "title": "Use the digital THX monitor, then you can back up the cross-platform circuit!",
    "category": "financial",
    "type": "Report",
    "created_by": "Brandon Deckow",
    "date_created": "2024-10-20T05:35:48.074Z",
    "origin_office": "regional_office",
    "status": "incoming"
  },
  {
    "id": "TASK-1415",
    "code": "FbD2vbRkEO",
    "qr": [
      "iSfVPRD6Zv",
      "lY3g786HZ8"
    ],
    "title": "I'll connect the mobile SMS application, that should card the GB sensor!",
    "category": "hr",
    "type": "Meeting",
    "created_by": "Kamron McGlynn",
    "date_created": "2024-10-07T21:25:19.665Z",
    "origin_office": "regional_office",
    "status": "completed"
  },
  {
    "id": "TASK-3178",
    "code": "8I5SGEfNOT",
    "qr": [
      "DbBdrjrs7S",
      "34JkM7vAco"
    ],
    "title": "Try to navigate the IP matrix, maybe it will navigate the bluetooth interface!",
    "category": "confidential",
    "type": "Document",
    "created_by": "Frieda Koss",
    "date_created": "2024-10-18T07:07:43.449Z",
    "origin_office": "header_office",
    "status": "completed"
  },
  {
    "id": "TASK-4954",
    "code": "1Rg4CjqqRf",
    "qr": [
      "BIoEa7NKWu",
      "Wp12g3daUF"
    ],
    "title": "The DNS driver is down, copy the neural bandwidth so we can program the XSS panel!",
    "category": "confidential",
    "type": "Document",
    "created_by": "Casandra Kohler",
    "date_created": "2024-10-03T21:16:13.287Z",
    "origin_office": "branch_office",
    "status": "incoming"
  },
  {
    "id": "TASK-9946",
    "code": "UbSRuEIwlW",
    "qr": [
      "oOu6yUUFsb",
      "VT3jwhPUen"
    ],
    "title": "You can't bypass the monitor without programming the back-end VGA circuit!",
    "category": "legal",
    "type": "Report",
    "created_by": "Carolyn Funk",
    "date_created": "2024-10-13T23:40:24.919Z",
    "origin_office": "header_office",
    "status": "outgoing"
  },
  {
    "id": "TASK-8800",
    "code": "KAQu0zVaLg",
    "qr": [
      "wdiSG1en7a",
      "NPgiW9xObv"
    ],
    "title": "I'll calculate the 1080p IB pixel, that should feed the SQL protocol!",
    "category": "financial",
    "type": "Document",
    "created_by": "Kenyon Durgan",
    "date_created": "2024-10-03T22:26:25.551Z",
    "origin_office": "header_office",
    "status": "completed"
  },
  {
    "id": "TASK-9161",
    "code": "HVtEpR1MUC",
    "qr": [
      "UcgVy5CZrN",
      "GZZZgJB6AI"
    ],
    "title": "I'll bypass the auxiliary IB program, that should interface the SSL pixel!",
    "category": "financial",
    "type": "Email",
    "created_by": "Sylvan Braun",
    "date_created": "2024-10-18T17:14:38.962Z",
    "origin_office": "branch_office",
    "status": "outgoing"
  },
  {
    "id": "TASK-8863",
    "code": "ODujSB3Z1k",
    "qr": [
      "RDQsXGKSL6",
      "tdNcP7Nteo"
    ],
    "title": "Try to connect the TLS system, maybe it will compress the solid state program!",
    "category": "confidential",
    "type": "Email",
    "created_by": "Charley Schmidt",
    "date_created": "2024-10-23T09:13:28.206Z",
    "origin_office": "header_office",
    "status": "outgoing"
  },
  {
    "id": "TASK-5775",
    "code": "u3EXkqO7sC",
    "qr": [
      "kYJKm4HsEu",
      "9NP5ZqKIm7"
    ],
    "title": "If we transmit the bandwidth, we can get to the SQL alarm through the solid state OCR card!",
    "category": "legal",
    "type": "Document",
    "created_by": "Lauriane Reilly",
    "date_created": "2024-10-11T07:07:22.952Z",
    "origin_office": "regional_office",
    "status": "recieved"
  },
  {
    "id": "TASK-7616",
    "code": "tKn2QU6z0L",
    "qr": [
      "PDLx7FekAT",
      "HgTtquKn2C"
    ],
    "title": "We need to reboot the mobile SAS pixel!",
    "category": "financial",
    "type": "Report",
    "created_by": "Vivianne Stark",
    "date_created": "2024-10-25T03:28:16.993Z",
    "origin_office": "regional_office",
    "status": "incoming"
  },
  {
    "id": "TASK-8808",
    "code": "TZH4YeIdIs",
    "qr": [
      "vzxhBjaRxC",
      "RVlbpFuwdS"
    ],
    "title": "We need to input the mobile AI bandwidth!",
    "category": "confidential",
    "type": "Document",
    "created_by": "Alayna Larkin",
    "date_created": "2024-10-25T14:03:23.549Z",
    "origin_office": "branch_office",
    "status": "completed"
  },
  {
    "id": "TASK-8289",
    "code": "mL1U0N7PFS",
    "qr": [
      "NbUPenEYWw",
      "M37v4O7G08"
    ],
    "title": "Try to reboot the HEX pixel, maybe it will override the primary bus!",
    "category": "confidential",
    "type": "Email",
    "created_by": "Lurline Hamill",
    "date_created": "2024-10-06T12:19:28.571Z",
    "origin_office": "branch_office",
    "status": "incoming"
  },
  {
    "id": "TASK-2054",
    "code": "CoIGfQwYar",
    "qr": [
      "JERd1ohXaa",
      "DM7uvPt3JX"
    ],
    "title": "Try to connect the OCR port, maybe it will calculate the neural array!",
    "category": "legal",
    "type": "Report",
    "created_by": "Judd Swaniawski",
    "date_created": "2024-10-20T07:48:40.728Z",
    "origin_office": "regional_office",
    "status": "outgoing"
  },
  {
    "id": "TASK-7191",
    "code": "g01ZJRx8K7",
    "qr": [
      "FRp5Rr6LlA",
      "LkuySuXsf5"
    ],
    "title": "We need to calculate the primary AGP array!",
    "category": "confidential",
    "type": "Report",
    "created_by": "Marianna Auer",
    "date_created": "2024-10-15T03:46:48.108Z",
    "origin_office": "header_office",
    "status": "outgoing"
  },
  {
    "id": "TASK-2400",
    "code": "9sIzVsSHE9",
    "qr": [
      "GUPxuZE6Hj",
      "QFv3xlCn3y"
    ],
    "title": "You can't override the capacitor without generating the multi-byte JBOD alarm!",
    "category": "legal",
    "type": "Email",
    "created_by": "Unique Shanahan",
    "date_created": "2024-10-03T04:45:43.730Z",
    "origin_office": "branch_office",
    "status": "completed"
  },
  {
    "id": "TASK-1267",
    "code": "Ed1TZRx7Wj",
    "qr": [
      "4F6qbET1PL",
      "CeCHeA0cSx"
    ],
    "title": "I'll bypass the optical DNS hard drive, that should pixel the SSL panel!",
    "category": "financial",
    "type": "Meeting",
    "created_by": "Melany Raynor",
    "date_created": "2024-10-08T20:14:13.497Z",
    "origin_office": "regional_office",
    "status": "outgoing"
  },
  {
    "id": "TASK-9296",
    "code": "wrnmGKjrHN",
    "qr": [
      "jPEsnCyvwY",
      "RVtCJdb0AL"
    ],
    "title": "Backing up the card won't do anything, we need to input the mobile IP application!",
    "category": "financial",
    "type": "Document",
    "created_by": "Damon Cronin",
    "date_created": "2024-10-07T00:24:50.391Z",
    "origin_office": "header_office",
    "status": "completed"
  },
  {
    "id": "TASK-7730",
    "code": "eYDCBPnvMO",
    "qr": [
      "iQOFg9bQIs",
      "Ykgz0CFHYA"
    ],
    "title": "I'll program the 1080p HTTP array, that should transmitter the DNS capacitor!",
    "category": "confidential",
    "type": "Report",
    "created_by": "Dolly Hickle",
    "date_created": "2024-10-21T07:37:27.662Z",
    "origin_office": "branch_office",
    "status": "outgoing"
  },
  {
    "id": "TASK-2839",
    "code": "lj5hZx4Bie",
    "qr": [
      "wB6AtW9jqH",
      "R2OBo60QoB"
    ],
    "title": "Try to navigate the API array, maybe it will hack the mobile card!",
    "category": "marketing",
    "type": "Document",
    "created_by": "Zena Gottlieb",
    "date_created": "2024-10-25T14:00:21.983Z",
    "origin_office": "regional_office",
    "status": "recieved"
  },
  {
    "id": "TASK-4458",
    "code": "ceOBKGDlO7",
    "qr": [
      "WFVHpqgfGx",
      "bty0hHPWkI"
    ],
    "title": "Use the wireless OCR bandwidth, then you can transmit the bluetooth panel!",
    "category": "confidential",
    "type": "Meeting",
    "created_by": "Cecile Crona",
    "date_created": "2024-10-27T00:07:30.955Z",
    "origin_office": "regional_office",
    "status": "completed"
  },
  {
    "id": "TASK-5002",
    "code": "JVIeDkqNRo",
    "qr": [
      "p5tLqfIyjm",
      "Sdj9cWUqZn"
    ],
    "title": "Try to calculate the IB sensor, maybe it will transmit the primary program!",
    "category": "financial",
    "type": "Meeting",
    "created_by": "Tina Gusikowski",
    "date_created": "2024-10-29T12:07:46.882Z",
    "origin_office": "regional_office",
    "status": "incoming"
  },
  {
    "id": "TASK-8263",
    "code": "maOuxhrQGq",
    "qr": [
      "IqhvbUSHKI",
      "mBK9oPBHPL"
    ],
    "title": "Use the back-end SDD alarm, then you can input the virtual feed!",
    "category": "financial",
    "type": "Document",
    "created_by": "Alfreda Auer",
    "date_created": "2024-10-12T02:18:59.041Z",
    "origin_office": "branch_office",
    "status": "incoming"
  },
  {
    "id": "TASK-1879",
    "code": "ZMh0xYbNON",
    "qr": [
      "saZJvkB7Kh",
      "34M6N99Ovi"
    ],
    "title": "I'll transmit the neural SAS card, that should matrix the VGA pixel!",
    "category": "marketing",
    "type": "Meeting",
    "created_by": "Alda Gusikowski",
    "date_created": "2024-10-04T08:51:23.239Z",
    "origin_office": "regional_office",
    "status": "incoming"
  },
  {
    "id": "TASK-8270",
    "code": "MVjwe9zd7N",
    "qr": [
      "G5NOH2pnUV",
      "qgen4cfZJU"
    ],
    "title": "Calculating the microchip won't do anything, we need to transmit the digital SMS monitor!",
    "category": "financial",
    "type": "Report",
    "created_by": "Richmond Ankunding",
    "date_created": "2024-10-29T20:50:07.307Z",
    "origin_office": "header_office",
    "status": "incoming"
  },
  {
    "id": "TASK-6326",
    "code": "H8v1fNDthK",
    "qr": [
      "K3Sz82T15v",
      "blK1v4xgci"
    ],
    "title": "The XML interface is down, reboot the neural microchip so we can calculate the SSD circuit!",
    "category": "hr",
    "type": "Meeting",
    "created_by": "Devante Little",
    "date_created": "2024-10-13T19:49:07.064Z",
    "origin_office": "branch_office",
    "status": "incoming"
  },
  {
    "id": "TASK-8481",
    "code": "WKOhqpUb89",
    "qr": [
      "LzJJROfIPB",
      "mqPQhjf8hQ"
    ],
    "title": "Try to generate the JSON transmitter, maybe it will bypass the 1080p hard drive!",
    "category": "financial",
    "type": "Meeting",
    "created_by": "Lauren Gleichner",
    "date_created": "2024-10-19T23:13:26.532Z",
    "origin_office": "header_office",
    "status": "outgoing"
  },
  {
    "id": "TASK-8712",
    "code": "MovapROEBR",
    "qr": [
      "f0HddpitlG",
      "EEVi8GPEWN"
    ],
    "title": "Use the haptic TLS port, then you can index the optical port!",
    "category": "hr",
    "type": "Report",
    "created_by": "Evert Lakin",
    "date_created": "2024-10-14T06:00:59.221Z",
    "origin_office": "header_office",
    "status": "incoming"
  },
  {
    "id": "TASK-4138",
    "code": "F0Vhss6D0L",
    "qr": [
      "zKiKuTbLa1",
      "6gfdurXDYS"
    ],
    "title": "Try to navigate the ASCII panel, maybe it will generate the back-end program!",
    "category": "confidential",
    "type": "Meeting",
    "created_by": "Amie Considine",
    "date_created": "2024-10-09T07:46:04.847Z",
    "origin_office": "header_office",
    "status": "recieved"
  },
  {
    "id": "TASK-2904",
    "code": "vfEwXLyx5H",
    "qr": [
      "P5qWtMtwZ8",
      "D8xqEtfHLS"
    ],
    "title": "We need to transmit the back-end XML feed!",
    "category": "legal",
    "type": "Email",
    "created_by": "Kevin Bahringer",
    "date_created": "2024-10-26T05:19:11.528Z",
    "origin_office": "header_office",
    "status": "completed"
  },
  {
    "id": "TASK-1061",
    "code": "zZaMM1zTJR",
    "qr": [
      "oLkNJQlwgU",
      "vHTASxDfVg"
    ],
    "title": "We need to bypass the cross-platform OCR sensor!",
    "category": "legal",
    "type": "Report",
    "created_by": "Petra Heathcote",
    "date_created": "2024-10-22T03:41:47.216Z",
    "origin_office": "header_office",
    "status": "outgoing"
  },
  {
    "id": "TASK-7890",
    "code": "5JaHv4A9tE",
    "qr": [
      "tQNJ4obkza",
      "8dpnJHjknI"
    ],
    "title": "If we input the capacitor, we can get to the AGP driver through the primary UDP interface!",
    "category": "legal",
    "type": "Meeting",
    "created_by": "Tracey Quigley-Hermiston",
    "date_created": "2024-10-08T15:41:48.850Z",
    "origin_office": "header_office",
    "status": "recieved"
  },
  {
    "id": "TASK-2786",
    "code": "qqamH7Home",
    "qr": [
      "QV0s87mkcR",
      "xZY2CwRo7h"
    ],
    "title": "If we quantify the matrix, we can get to the SSD alarm through the haptic VGA circuit!",
    "category": "hr",
    "type": "Report",
    "created_by": "Justine Hirthe",
    "date_created": "2024-10-13T18:54:28.697Z",
    "origin_office": "regional_office",
    "status": "recieved"
  },
  {
    "id": "TASK-3824",
    "code": "SoroGtk5Pw",
    "qr": [
      "NIkGiQOvPL",
      "GAR0beYdeT"
    ],
    "title": "Try to bypass the DNS port, maybe it will transmit the haptic driver!",
    "category": "marketing",
    "type": "Document",
    "created_by": "Timmothy Oberbrunner",
    "date_created": "2024-11-01T01:00:01.010Z",
    "origin_office": "regional_office",
    "status": "completed"
  },
  {
    "id": "TASK-7745",
    "code": "tmJ5JlsbnY",
    "qr": [
      "X8Jr1lK3Q0",
      "EVwUjx3RMn"
    ],
    "title": "Try to input the SSL panel, maybe it will connect the multi-byte panel!",
    "category": "legal",
    "type": "Email",
    "created_by": "Chadd Lehner",
    "date_created": "2024-10-23T10:53:33.107Z",
    "origin_office": "branch_office",
    "status": "incoming"
  },
  {
    "id": "TASK-1470",
    "code": "N8XEYND346",
    "qr": [
      "PaTUsjOlSL",
      "ZsPAmSt2ew"
    ],
    "title": "You can't compress the monitor without quantifying the optical COM program!",
    "category": "legal",
    "type": "Report",
    "created_by": "Kathleen Zemlak",
    "date_created": "2024-10-28T08:26:00.954Z",
    "origin_office": "branch_office",
    "status": "recieved"
  },
  {
    "id": "TASK-5216",
    "code": "aSbIH7THvz",
    "qr": [
      "3g2jrQsLNU",
      "Uq5FbLEmGQ"
    ],
    "title": "You can't generate the array without transmitting the mobile XSS firewall!",
    "category": "hr",
    "type": "Document",
    "created_by": "Jovany Kovacek",
    "date_created": "2024-10-31T19:54:27.206Z",
    "origin_office": "header_office",
    "status": "completed"
  },
  {
    "id": "TASK-4007",
    "code": "DpA34uVNSU",
    "qr": [
      "pUh3YhYdtk",
      "uVH4lCQi1z"
    ],
    "title": "The THX pixel is down, override the 1080p array so we can index the SDD driver!",
    "category": "marketing",
    "type": "Document",
    "created_by": "Fae Herman",
    "date_created": "2024-10-19T13:11:46.660Z",
    "origin_office": "header_office",
    "status": "outgoing"
  },
  {
    "id": "TASK-8563",
    "code": "D240eM490m",
    "qr": [
      "rPn0bLERRf",
      "oX5wkVz689"
    ],
    "title": "If we navigate the array, we can get to the TLS application through the optical HEX microchip!",
    "category": "financial",
    "type": "Report",
    "created_by": "Allison Walker",
    "date_created": "2024-10-05T06:25:54.354Z",
    "origin_office": "branch_office",
    "status": "recieved"
  },
  {
    "id": "TASK-9412",
    "code": "1Ts3Kts46w",
    "qr": [
      "zsqCeIenkj",
      "nQS9A1y7QX"
    ],
    "title": "If we synthesize the capacitor, we can get to the SMTP pixel through the optical THX bus!",
    "category": "legal",
    "type": "Document",
    "created_by": "Dewitt Jaskolski",
    "date_created": "2024-10-05T17:38:07.591Z",
    "origin_office": "branch_office",
    "status": "outgoing"
  },
  {
    "id": "TASK-5075",
    "code": "wMnaFX8Vr3",
    "qr": [
      "xCQNZnrjTv",
      "nAc74L2BxY"
    ],
    "title": "If we calculate the circuit, we can get to the EXE pixel through the bluetooth IB matrix!",
    "category": "marketing",
    "type": "Email",
    "created_by": "Eveline Treutel",
    "date_created": "2024-10-03T18:19:35.206Z",
    "origin_office": "header_office",
    "status": "recieved"
  },
  {
    "id": "TASK-2668",
    "code": "OmxSNBTiLA",
    "qr": [
      "Yt9scudD3o",
      "dwCzTlaXJV"
    ],
    "title": "Use the online GB bus, then you can compress the optical application!",
    "category": "confidential",
    "type": "Report",
    "created_by": "Domenico Runte-McKenzie",
    "date_created": "2024-10-31T16:34:26.455Z",
    "origin_office": "regional_office",
    "status": "recieved"
  },
  {
    "id": "TASK-9077",
    "code": "vv2Qe1CjuW",
    "qr": [
      "ETxiFJMk9o",
      "SJbvAUDELH"
    ],
    "title": "If we calculate the capacitor, we can get to the API feed through the redundant THX program!",
    "category": "marketing",
    "type": "Report",
    "created_by": "Estelle Kling",
    "date_created": "2024-10-18T07:02:03.691Z",
    "origin_office": "regional_office",
    "status": "completed"
  },
  {
    "id": "TASK-2231",
    "code": "bjEl3bgUcX",
    "qr": [
      "Y1JJhR3wKw",
      "rOcFrsdyEV"
    ],
    "title": "We need to parse the neural PCI circuit!",
    "category": "confidential",
    "type": "Document",
    "created_by": "Ruthe Heathcote",
    "date_created": "2024-10-04T21:39:45.524Z",
    "origin_office": "branch_office",
    "status": "completed"
  },
  {
    "id": "TASK-8917",
    "code": "VWGdU2jzkF",
    "qr": [
      "upQEn4KaoI",
      "edHNIJ3Qnt"
    ],
    "title": "We need to program the mobile RAM transmitter!",
    "category": "financial",
    "type": "Report",
    "created_by": "Karson Brekke",
    "date_created": "2024-11-01T08:36:04.585Z",
    "origin_office": "header_office",
    "status": "incoming"
  },
  {
    "id": "TASK-3058",
    "code": "jgKVfsRhlE",
    "qr": [
      "beW29xmUNW",
      "GmlndrRm6c"
    ],
    "title": "I'll bypass the multi-byte TCP pixel, that should driver the TCP driver!",
    "category": "confidential",
    "type": "Meeting",
    "created_by": "Ole Pollich",
    "date_created": "2024-10-12T17:51:04.487Z",
    "origin_office": "branch_office",
    "status": "completed"
  },
  {
    "id": "TASK-3292",
    "code": "z9lndETpZW",
    "qr": [
      "aLrplWzHER",
      "hhSB5wacNC"
    ],
    "title": "We need to connect the 1080p IB card!",
    "category": "hr",
    "type": "Meeting",
    "created_by": "Hilton Volkman",
    "date_created": "2024-10-19T23:15:37.376Z",
    "origin_office": "header_office",
    "status": "recieved"
  },
  {
    "id": "TASK-9832",
    "code": "xL4GyuokJW",
    "qr": [
      "V2aC1g6nix",
      "G64c027SqJ"
    ],
    "title": "Compressing the panel won't do anything, we need to synthesize the multi-byte SDD monitor!",
    "category": "hr",
    "type": "Email",
    "created_by": "Ashton Nikolaus",
    "date_created": "2024-10-31T15:24:26.505Z",
    "origin_office": "regional_office",
    "status": "outgoing"
  },
  {
    "id": "TASK-7466",
    "code": "lvX8uKx9SX",
    "qr": [
      "yU4hYzRNcg",
      "ognFPNeqcs"
    ],
    "title": "Try to quantify the ASCII system, maybe it will copy the mobile hard drive!",
    "category": "financial",
    "type": "Meeting",
    "created_by": "Emma Hansen",
    "date_created": "2024-10-10T09:19:34.398Z",
    "origin_office": "header_office",
    "status": "completed"
  },
  {
    "id": "TASK-9106",
    "code": "LudF6iIa7D",
    "qr": [
      "I3gqeJaVqR",
      "AhMV7F5gHJ"
    ],
    "title": "Use the redundant SMS panel, then you can compress the haptic card!",
    "category": "financial",
    "type": "Report",
    "created_by": "Brady Hermiston",
    "date_created": "2024-10-26T03:21:34.161Z",
    "origin_office": "header_office",
    "status": "completed"
  },
  {
    "id": "TASK-9271",
    "code": "AzRfT8QCuP",
    "qr": [
      "FvEU3LIyOt",
      "JZOFZ1aacz"
    ],
    "title": "You can't hack the interface without compressing the virtual XSS driver!",
    "category": "legal",
    "type": "Email",
    "created_by": "Jeanie Lockman",
    "date_created": "2024-10-08T01:06:09.816Z",
    "origin_office": "regional_office",
    "status": "outgoing"
  }
]